pype_schema/__init__.py
pype_schema/connection.py
pype_schema/epyt_utils.py
pype_schema/logbook.py
pype_schema/node.py
pype_schema/operations.py
pype_schema/parse_json.py
pype_schema/tag.py
pype_schema/units.py
pype_schema/utils.py
pype_schema/visualize.py
pype_schema/data/__init__.py
pype_schema/data/desal_sample.json
pype_schema/data/sample_data.csv
pype_schema/data/unit_definitions.txt
pype_schema/data/wrrf_sample.json
pype_schema/data/wrrf_sample_algebraic.json
pype_schema-0.7.2.dist-info/licenses/LICENSE
pype_schema-0.7.2.dist-info/METADATA
pype_schema-0.7.2.dist-info/WHEEL
pype_schema-0.7.2.dist-info/top_level.txt
pype_schema-0.7.2.dist-info/RECORD
