Metadata-Version: 2.4
Name: pype-schema
Version: 0.7.2
Summary: Class hierarchy to represent configurations of process engineering systems.
Home-page: https://github.com/we3lab/pype-schema
Author: WE3 Lab
Author-email: fchapin@stanford.edu
Keywords: pype-schema
Classifier: Development Status :: 2 - Pre-Alpha
Classifier: Intended Audience :: Developers
Classifier: License :: Free for non-commercial use
Classifier: Natural Language :: English
Classifier: Programming Language :: Python :: 3.10
Classifier: Programming Language :: Python :: 3.11
Classifier: Programming Language :: Python :: 3.12
Classifier: Programming Language :: Python :: 3.13
Requires-Python: >=3.10
License-File: LICENSE
Requires-Dist: pint>=0.19.2
Requires-Dist: networkx>=2.8.5
Requires-Dist: pyvis>=0.3.0
Requires-Dist: matplotlib>=3.5.2
Requires-Dist: pandas>=1.4.0
Requires-Dist: numpy>=1.22.1
Requires-Dist: scipy>=1.8.0
Requires-Dist: epyt>=1.0.0
Provides-Extra: setup
Provides-Extra: test
Requires-Dist: black>=22.3.0; extra == "test"
Requires-Dist: flake8>=4.0.0; extra == "test"
Requires-Dist: codecov>=2.1.4; extra == "test"
Requires-Dist: pytest>=6.2.5; extra == "test"
Requires-Dist: pytest-cov>=3.0.0; extra == "test"
Requires-Dist: pytest-html>=3.1.1; extra == "test"
Provides-Extra: dev
Requires-Dist: black>=22.3.0; extra == "dev"
Requires-Dist: flake8>=4.0.0; extra == "dev"
Requires-Dist: codecov>=2.1.4; extra == "dev"
Requires-Dist: pytest>=6.2.5; extra == "dev"
Requires-Dist: pytest-cov>=3.0.0; extra == "dev"
Requires-Dist: pytest-html>=3.1.1; extra == "dev"
Requires-Dist: tox>=3.24.5; extra == "dev"
Requires-Dist: Sphinx==7.0.1; extra == "dev"
Requires-Dist: sphinx-rtd-theme==2.0.0; extra == "dev"
Provides-Extra: all
Requires-Dist: pint>=0.19.2; extra == "all"
Requires-Dist: networkx>=2.8.5; extra == "all"
Requires-Dist: pyvis>=0.3.0; extra == "all"
Requires-Dist: matplotlib>=3.5.2; extra == "all"
Requires-Dist: pandas>=1.4.0; extra == "all"
Requires-Dist: numpy>=1.22.1; extra == "all"
Requires-Dist: scipy>=1.8.0; extra == "all"
Requires-Dist: epyt>=1.0.0; extra == "all"
Requires-Dist: black>=22.3.0; extra == "all"
Requires-Dist: flake8>=4.0.0; extra == "all"
Requires-Dist: codecov>=2.1.4; extra == "all"
Requires-Dist: pytest>=6.2.5; extra == "all"
Requires-Dist: pytest-cov>=3.0.0; extra == "all"
Requires-Dist: pytest-html>=3.1.1; extra == "all"
Requires-Dist: tox>=3.24.5; extra == "all"
Requires-Dist: Sphinx==7.0.1; extra == "all"
Requires-Dist: sphinx-rtd-theme==2.0.0; extra == "all"
Dynamic: author
Dynamic: author-email
Dynamic: classifier
Dynamic: description
Dynamic: description-content-type
Dynamic: home-page
Dynamic: keywords
Dynamic: license-file
Dynamic: provides-extra
Dynamic: requires-dist
Dynamic: requires-python
Dynamic: summary
